{
  "language_code": "slk",
  "language_probability": 1.0,
  "text": "Poviete k tomuto niečo, čo ste si pozreli? Takže ako sa tam prejavovali znaky stredovekej literatúry? Sviešť, náboženstvo. Aké? Je tam aj Boh, aj zelený boh. Vo svojej hlave máme celkom iný vzťah k nemu. Zaujíma nás len nejaké veci. Áno, čiže aj ten jeho život, aj tie straty, ktoré vlastne v živote zažíva, že on stratí ten krahulec, vníma ako súčasť nejakého Božieho plánu. Hej, čiže veľmi kľúčová pre nich viera, náboženstvo, kresťanstvo. Čo ešte? Povedal som, že idealizácia. Tam pomáhla to, že mal tú ženu, že najkrajšiu zo žiadnych tvárou veľmi okrášlene zlatými perami, perlami a... Počkaj, ale ten idealizovaný je tu kto? To dieťa, ten Konštantín. Čo je tu vlastne také vzorové? Vynikal veľmi bystrou pamäťou. Všetci sa čudovali. Áno, aký bol úžasný? Bystrou pamäťou, svojím naozaj, tým účenosťou ako vynikal. A čím to bolo dané? Lebo čo si vybral za celoživotnú spoločníčku? Koho? Svoju sestru. Múdrosť si vybral. Sofiu, svoju sestru. Ty si mimo. Ty si zas v Oha! Si malá babka nadavka. Rozhlas stredovekej literatúry na Slovensku. Naozaj súvislosti týkajúce sa Konštantína tej byzantskej misie? Významnosť osobnosti označenej ako filozof počiatkov stredovekej literatúry. Konštantín je to šíriteľ kresťanstva, zostavovateľ písma, prekladateľ prvých textov a autor prvej básne. Ešte niečo významné spravil? Že staroslovienčinu ako liturgický jazyk obhajoval a dokonca dosiahol jej schválenie? Čiže vediete aj význam Konštantína. Legendu sme spomínali. Všimnite si potom tie otázky štyri, päť, šesť. Presne preto, že... Máte tam to štristické využitie. Ako to vlastne vieme využiť? Čo je to pre nás? V čom je to zaujímavé? Vyhľadaj v texte synonymá slova slovesa povedať, Hovoria. Rozprávam. Hovoriac, že hovoriť. Rozprávať. Rozprávať. Napríklad. Toto sme vlastne vytvorili synonymický rad k tomuto slovu. Ešte niečo? Pridavné mená z posledného odseku vieme antonymá? Ako by ste dali, keď máme bystrú pamäť? Čo je opakom bystrej pamäti? Tupá. Tupá. Tupá pamäť napríklad. Potom tam máme, čo ja viem, kde sme tam ešte mali aké prídavné mená? Pozemský. Smutný. Božie riadenie. Čo by ste dali k slovu Božie ako antonym? Ľudske? Ateistické riadenie. Ľudske? Pekelné riadenie. Ľudské by sa dalo v istom kontexte, v istom kontexte by sa dalo skôr pekelné, diabolské. Aké je antoným k slovu smutný? Šťastný, veselý, radostný, akékoľvek antonym. Čiže aj veď ich prakticky z toho textu. Z toho činy. Tá písomka. Zatvor úst, povedzme, že zajtra budem robiť, čo mám Hamleta vypraviť. Ja som zajtrajšok už dávno nebudem. Radek taký, že čo zajtra, čo? Uzávierky.",
  "words": [
    {
      "text": "Poviete",
      "start": 0.14,
      "end": 0.36,
      "type": "word"
    },
    {
      "text": " ",
      "start": 0.36,
      "end": 0.36,
      "type": "spacing"
    },
    {
      "text": "k",
      "start": 0.36,
      "end": 0.36,
      "type": "word"
    },
    {
      "text": " ",
      "start": 0.36,
      "end": 0.439,
      "type": "spacing"
    },
    {
      "text": "tomuto",
      "start": 0.439,
      "end": 0.799,
      "type": "word"
    },
    {
      "text": " ",
      "start": 0.799,
      "end": 0.799,
      "type": "spacing"
    },
    {
      "text": "niečo,",
      "start": 0.799,
      "end": 1.139,
      "type": "word"
    },
    {
      "text": " ",
      "start": 1.139,
      "end": 1.139,
      "type": "spacing"
    },
    {
      "text": "čo",
      "start": 1.139,
      "end": 1.279,
      "type": "word"
    },
    {
      "text": " ",
      "start": 1.279,
      "end": 1.279,
      "type": "spacing"
    },
    {
      "text": "ste",
      "start": 1.279,
      "end": 1.44,
      "type": "word"
    },
    {
      "text": " ",
      "start": 1.44,
      "end": 1.5,
      "type": "spacing"
    },
    {
      "text": "si",
      "start": 1.5,
      "end": 1.699,
      "type": "word"
    },
    {
      "text": " ",
      "start": 1.699,
      "end": 1.699,
      "type": "spacing"
    },
    {
      "text": "pozreli?",
      "start": 1.699,
      "end": 2.34,
      "type": "word"
    },
    {
      "text": " ",
      "start": 2.34,
      "end": 4.219,
      "type": "spacing"
    },
    {
      "text": "Takže",
      "start": 4.219,
      "end": 4.719,
      "type": "word"
    },
    {
      "text": " ",
      "start": 4.719,
      "end": 5.299,
      "type": "spacing"
    },
    {
      "text": "ako",
      "start": 5.299,
      "end": 5.699,
      "type": "word"
    },
    {
      "text": " ",
      "start": 5.699,
      "end": 5.699,
      "type": "spacing"
    },
    {
      "text": "sa",
      "start": 5.699,
      "end": 5.899,
      "type": "word"
    },
    {
      "text": " ",
      "start": 5.899,
      "end": 5.9,
      "type": "spacing"
    },
    {
      "text": "tam",
      "start": 5.9,
      "end": 6.099,
      "type": "word"
    },
    {
      "text": " ",
      "start": 6.099,
      "end": 6.119,
      "type": "spacing"
    },
    {
      "text": "prejavovali",
      "start": 6.119,
      "end": 6.679,
      "type": "word"
    },
    {
      "text": " ",
      "start": 6.679,
      "end": 6.739,
      "type": "spacing"
    },
    {
      "text": "znaky",
      "start": 6.739,
      "end": 7.079,
      "type": "word"
    },
    {
      "text": " ",
      "start": 7.079,
      "end": 7.099,
      "type": "spacing"
    },
    {
      "text": "stredovekej",
      "start": 7.099,
      "end": 7.779,
      "type": "word"
    },
    {
      "text": " ",
      "start": 7.779,
      "end": 7.799,
      "type": "spacing"
    },
    {
      "text": "literatúry?",
      "start": 7.799,
      "end": 8.599,
      "type": "word"
    },
    {
      "text": " ",
      "start": 8.599,
      "end": 10.38,
      "type": "spacing"
    },
    {
      "text": "Sviešť,",
      "start": 10.38,
      "end": 10.72,
      "type": "word"
    },
    {
      "text": " ",
      "start": 10.72,
      "end": 10.899,
      "type": "spacing"
    },
    {
      "text": "náboženstvo.",
      "start": 10.899,
      "end": 12.339,
      "type": "word"
    },
    {
      "text": " ",
      "start": 12.339,
      "end": 13.819,
      "type": "spacing"
    },
    {
      "text": "Aké?",
      "start": 13.819,
      "end": 14.219,
      "type": "word"
    },
    {
      "text": " ",
      "start": 14.219,
      "end": 14.219,
      "type": "spacing"
    },
    {
      "text": "Je",
      "start": 14.219,
      "end": 14.339,
      "type": "word"
    },
    {
      "text": " ",
      "start": 14.339,
      "end": 14.479,
      "type": "spacing"
    },
    {
      "text": "tam",
      "start": 14.479,
      "end": 14.719,
      "type": "word"
    },
    {
      "text": " ",
      "start": 14.719,
      "end": 14.719,
      "type": "spacing"
    },
    {
      "text": "aj",
      "start": 14.719,
      "end": 14.859,
      "type": "word"
    },
    {
      "text": " ",
      "start": 14.859,
      "end": 15.899,
      "type": "spacing"
    },
    {
      "text": "Boh,",
      "start": 15.899,
      "end": 16.159,
      "type": "word"
    },
    {
      "text": " ",
      "start": 16.159,
      "end": 16.159,
      "type": "spacing"
    },
    {
      "text": "aj",
      "start": 16.159,
      "end": 16.22,
      "type": "word"
    },
    {
      "text": " ",
      "start": 16.22,
      "end": 16.299,
      "type": "spacing"
    },
    {
      "text": "zelený",
      "start": 16.299,
      "end": 16.7,
      "type": "word"
    },
    {
      "text": " ",
      "start": 16.7,
      "end": 16.739,
      "type": "spacing"
    },
    {
      "text": "boh.",
      "start": 16.739,
      "end": 17.459,
      "type": "word"
    },
    {
      "text": " ",
      "start": 17.459,
      "end": 17.459,
      "type": "spacing"
    },
    {
      "text": "Vo",
      "start": 17.459,
      "end": 17.479,
      "type": "word"
    },
    {
      "text": " ",
      "start": 17.479,
      "end": 17.6,
      "type": "spacing"
    },
    {
      "text": "svojej",
      "start": 17.6,
      "end": 17.799,
      "type": "word"
    },
    {
      "text": " ",
      "start": 17.799,
      "end": 17.84,
      "type": "spacing"
    },
    {
      "text": "hlave",
      "start": 17.84,
      "end": 18.02,
      "type": "word"
    },
    {
      "text": " ",
      "start": 18.02,
      "end": 18.02,
      "type": "spacing"
    },
    {
      "text": "máme",
      "start": 18.02,
      "end": 18.02,
      "type": "word"
    },
    {
      "text": " ",
      "start": 18.02,
      "end": 18.459,
      "type": "spacing"
    },
    {
      "text": "celkom",
      "start": 18.459,
      "end": 18.939,
      "type": "word"
    },
    {
      "text": " ",
      "start": 18.939,
      "end": 18.939,
      "type": "spacing"
    },
    {
      "text": "iný",
      "start": 18.939,
      "end": 19.18,
      "type": "word"
    },
    {
      "text": " ",
      "start": 19.18,
      "end": 19.239,
      "type": "spacing"
    },
    {
      "text": "vzťah",
      "start": 19.239,
      "end": 19.78,
      "type": "word"
    },
    {
      "text": " ",
      "start": 19.78,
      "end": 19.78,
      "type": "spacing"
    },
    {
      "text": "k",
      "start": 19.78,
      "end": 19.819,
      "type": "word"
    },
    {
      "text": " ",
      "start": 19.819,
      "end": 19.819,
      "type": "spacing"
    },
    {
      "text": "nemu.",
      "start": 19.819,
      "end": 20.199,
      "type": "word"
    },
    {
      "text": " ",
      "start": 20.199,
      "end": 20.219,
      "type": "spacing"
    },
    {
      "text": "Zaujíma",
      "start": 20.219,
      "end": 20.519,
      "type": "word"
    },
    {
      "text": " ",
      "start": 20.519,
      "end": 20.619,
      "type": "spacing"
    },
    {
      "text": "nás",
      "start": 20.619,
      "end": 20.799,
      "type": "word"
    },
    {
      "text": " ",
      "start": 20.799,
      "end": 20.879,
      "type": "spacing"
    },
    {
      "text": "len",
      "start": 20.879,
      "end": 21.039,
      "type": "word"
    },
    {
      "text": " ",
      "start": 21.039,
      "end": 21.039,
      "type": "spacing"
    },
    {
      "text": "nejaké",
      "start": 21.039,
      "end": 21.279,
      "type": "word"
    },
    {
      "text": " ",
      "start": 21.279,
      "end": 21.299,
      "type": "spacing"
    },
    {
      "text": "veci.",
      "start": 21.299,
      "end": 21.659,
      "type": "word"
    },
    {
      "text": " ",
      "start": 21.659,
      "end": 22.219,
      "type": "spacing"
    },
    {
      "text": "Áno,",
      "start": 22.219,
      "end": 22.639,
      "type": "word"
    },
    {
      "text": " ",
      "start": 22.639,
      "end": 22.639,
      "type": "spacing"
    },
    {
      "text": "čiže",
      "start": 22.639,
      "end": 22.92,
      "type": "word"
    },
    {
      "text": " ",
      "start": 22.92,
      "end": 22.92,
      "type": "spacing"
    },
    {
      "text": "aj",
      "start": 22.92,
      "end": 23.039,
      "type": "word"
    },
    {
      "text": " ",
      "start": 23.039,
      "end": 23.059,
      "type": "spacing"
    },
    {
      "text": "ten",
      "start": 23.059,
      "end": 23.22,
      "type": "word"
    },
    {
      "text": " ",
      "start": 23.22,
      "end": 23.239,
      "type": "spacing"
    },
    {
      "text": "jeho",
      "start": 23.239,
      "end": 23.519,
      "type": "word"
    },
    {
      "text": " ",
      "start": 23.519,
      "end": 23.539,
      "type": "spacing"
    },
    {
      "text": "život,",
      "start": 23.539,
      "end": 23.86,
      "type": "word"
    },
    {
      "text": " ",
      "start": 23.86,
      "end": 23.92,
      "type": "spacing"
    },
    {
      "text": "aj",
      "start": 23.92,
      "end": 24.059,
      "type": "word"
    },
    {
      "text": " ",
      "start": 24.059,
      "end": 24.059,
      "type": "spacing"
    },
    {
      "text": "tie",
      "start": 24.059,
      "end": 24.219,
      "type": "word"
    },
    {
      "text": " ",
      "start": 24.219,
      "end": 24.219,
      "type": "spacing"
    },
    {
      "text": "straty,",
      "start": 24.219,
      "end": 24.659,
      "type": "word"
    },
    {
      "text": " ",
      "start": 24.659,
      "end": 24.68,
      "type": "spacing"
    },
    {
      "text": "ktoré",
      "start": 24.68,
      "end": 24.979,
      "type": "word"
    },
    {
      "text": " ",
      "start": 24.979,
      "end": 25.0,
      "type": "spacing"
    },
    {
      "text": "vlastne",
      "start": 25.0,
      "end": 25.34,
      "type": "word"
    },
    {
      "text": " ",
      "start": 25.34,
      "end": 25.34,
      "type": "spacing"
    },
    {
      "text": "v",
      "start": 25.34,
      "end": 25.38,
      "type": "word"
    },
    {
      "text": " ",
      "start": 25.38,
      "end": 25.399,
      "type": "spacing"
    },
    {
      "text": "živote",
      "start": 25.399,
      "end": 25.76,
      "type": "word"
    },
    {
      "text": " ",
      "start": 25.76,
      "end": 25.76,
      "type": "spacing"
    },
    {
      "text": "zažíva,",
      "start": 25.76,
      "end": 26.299,
      "type": "word"
    },
    {
      "text": " ",
      "start": 26.299,
      "end": 26.379,
      "type": "spacing"
    },
    {
      "text": "že",
      "start": 26.379,
      "end": 26.479,
      "type": "word"
    },
    {
      "text": " ",
      "start": 26.479,
      "end": 26.479,
      "type": "spacing"
    },
    {
      "text": "on",
      "start": 26.479,
      "end": 26.559,
      "type": "word"
    },
    {
      "text": " ",
      "start": 26.559,
      "end": 26.659,
      "type": "spacing"
    },
    {
      "text": "stratí",
      "start": 26.659,
      "end": 27.039,
      "type": "word"
    },
    {
      "text": " ",
      "start": 27.039,
      "end": 27.059,
      "type": "spacing"
    },
    {
      "text": "ten",
      "start": 27.059,
      "end": 27.219,
      "type": "word"
    },
    {
      "text": " ",
      "start": 27.219,
      "end": 27.239,
      "type": "spacing"
    },
    {
      "text": "krahulec,",
      "start": 27.239,
      "end": 27.979,
      "type": "word"
    },
    {
      "text": " ",
      "start": 27.979,
      "end": 28.299,
      "type": "spacing"
    },
    {
      "text": "vníma",
      "start": 28.299,
      "end": 28.68,
      "type": "word"
    },
    {
      "text": " ",
      "start": 28.68,
      "end": 28.699,
      "type": "spacing"
    },
    {
      "text": "ako",
      "start": 28.699,
      "end": 29.159,
      "type": "word"
    },
    {
      "text": " ",
      "start": 29.159,
      "end": 30.0,
      "type": "spacing"
    },
    {
      "text": "súčasť",
      "start": 30.0,
      "end": 30.559,
      "type": "word"
    },
    {
      "text": " ",
      "start": 30.559,
      "end": 30.559,
      "type": "spacing"
    },
    {
      "text": "nejakého",
      "start": 30.559,
      "end": 30.939,
      "type": "word"
    },
    {
      "text": " ",
      "start": 30.939,
      "end": 30.979,
      "type": "spacing"
    },
    {
      "text": "Božieho",
      "start": 30.979,
      "end": 31.659,
      "type": "word"
    },
    {
      "text": " ",
      "start": 31.659,
      "end": 32.259,
      "type": "spacing"
    },
    {
      "text": "plánu.",
      "start": 32.259,
      "end": 32.959,
      "type": "word"
    },
    {
      "text": " ",
      "start": 32.959,
      "end": 33.099,
      "type": "spacing"
    },
    {
      "text": "Hej,",
      "start": 33.099,
      "end": 33.38,
      "type": "word"
    },
    {
      "text": " ",
      "start": 33.38,
      "end": 33.399,
      "type": "spacing"
    },
    {
      "text": "čiže",
      "start": 33.399,
      "end": 33.68,
      "type": "word"
    },
    {
      "text": " ",
      "start": 33.68,
      "end": 33.7,
      "type": "spacing"
    },
    {
      "text": "veľmi",
      "start": 33.7,
      "end": 34.059,
      "type": "word"
    },
    {
      "text": " ",
      "start": 34.059,
      "end": 34.119,
      "type": "spacing"
    },
    {
      "text": "kľúčová",
      "start": 34.119,
      "end": 34.639,
      "type": "word"
    },
    {
      "text": " ",
      "start": 34.639,
      "end": 34.68,
      "type": "spacing"
    },
    {
      "text": "pre",
      "start": 34.68,
      "end": 34.86,
      "type": "word"
    },
    {
      "text": " ",
      "start": 34.86,
      "end": 34.86,
      "type": "spacing"
    },
    {
      "text": "nich",
      "start": 34.86,
      "end": 35.06,
      "type": "word"
    },
    {
      "text": " ",
      "start": 35.06,
      "end": 35.079,
      "type": "spacing"
    },
    {
      "text": "viera,",
      "start": 35.079,
      "end": 35.56,
      "type": "word"
    },
    {
      "text": " ",
      "start": 35.56,
      "end": 35.919,
      "type": "spacing"
    },
    {
      "text": "náboženstvo,",
      "start": 35.919,
      "end": 36.639,
      "type": "word"
    },
    {
      "text": " ",
      "start": 36.639,
      "end": 36.639,
      "type": "spacing"
    },
    {
      "text": "kresťanstvo.",
      "start": 36.639,
      "end": 37.439,
      "type": "word"
    },
    {
      "text": " ",
      "start": 37.439,
      "end": 37.439,
      "type": "spacing"
    },
    {
      "text": "Čo",
      "start": 37.439,
      "end": 37.579,
      "type": "word"
    },
    {
      "text": " ",
      "start": 37.579,
      "end": 37.579,
      "type": "spacing"
    },
    {
      "text": "ešte?",
      "start": 37.579,
      "end": 37.999,
      "type": "word"
    },
    {
      "text": " ",
      "start": 37.999,
      "end": 38.939,
      "type": "spacing"
    },
    {
      "text": "Povedal",
      "start": 38.939,
      "end": 39.18,
      "type": "word"
    },
    {
      "text": " ",
      "start": 39.18,
      "end": 39.219,
      "type": "spacing"
    },
    {
      "text": "som,",
      "start": 39.219,
      "end": 39.479,
      "type": "word"
    },
    {
      "text": " ",
      "start": 39.479,
      "end": 39.639,
      "type": "spacing"
    },
    {
      "text": "že",
      "start": 39.639,
      "end": 39.759,
      "type": "word"
    },
    {
      "text": " ",
      "start": 39.759,
      "end": 40.819,
      "type": "spacing"
    },
    {
      "text": "idealizácia.",
      "start": 40.819,
      "end": 41.999,
      "type": "word"
    },
    {
      "text": " ",
      "start": 41.999,
      "end": 42.559,
      "type": "spacing"
    },
    {
      "text": "Tam",
      "start": 42.559,
      "end": 42.74,
      "type": "word"
    },
    {
      "text": " ",
      "start": 42.74,
      "end": 43.36,
      "type": "spacing"
    },
    {
      "text": "pomáhla",
      "start": 43.36,
      "end": 43.959,
      "type": "word"
    },
    {
      "text": " ",
      "start": 43.959,
      "end": 44.419,
      "type": "spacing"
    },
    {
      "text": "to,",
      "start": 44.419,
      "end": 44.739,
      "type": "word"
    },
    {
      "text": " ",
      "start": 44.739,
      "end": 44.86,
      "type": "spacing"
    },
    {
      "text": "že",
      "start": 44.86,
      "end": 45.02,
      "type": "word"
    },
    {
      "text": " ",
      "start": 45.02,
      "end": 45.139,
      "type": "spacing"
    },
    {
      "text": "mal",
      "start": 45.139,
      "end": 45.52,
      "type": "word"
    },
    {
      "text": " ",
      "start": 45.52,
      "end": 45.659,
      "type": "spacing"
    },
    {
      "text": "tú",
      "start": 45.659,
      "end": 45.84,
      "type": "word"
    },
    {
      "text": " ",
      "start": 45.84,
      "end": 45.84,
      "type": "spacing"
    },
    {
      "text": "ženu,",
      "start": 45.84,
      "end": 46.159,
      "type": "word"
    },
    {
      "text": " ",
      "start": 46.159,
      "end": 47.219,
      "type": "spacing"
    },
    {
      "text": "že",
      "start": 47.219,
      "end": 47.239,
      "type": "word"
    },
    {
      "text": " ",
      "start": 47.239,
      "end": 47.259,
      "type": "spacing"
    },
    {
      "text": "najkrajšiu",
      "start": 47.259,
      "end": 47.959,
      "type": "word"
    },
    {
      "text": " ",
      "start": 47.959,
      "end": 48.0,
      "type": "spacing"
    },
    {
      "text": "zo",
      "start": 48.0,
      "end": 48.159,
      "type": "word"
    },
    {
      "text": " ",
      "start": 48.159,
      "end": 48.159,
      "type": "spacing"
    },
    {
      "text": "žiadnych",
      "start": 48.159,
      "end": 48.459,
      "type": "word"
    },
    {
      "text": " ",
      "start": 48.459,
      "end": 48.659,
      "type": "spacing"
    },
    {
      "text": "tvárou",
      "start": 48.659,
      "end": 49.02,
      "type": "word"
    },
    {
      "text": " ",
      "start": 49.02,
      "end": 49.039,
      "type": "spacing"
    },
    {
      "text": "veľmi",
      "start": 49.039,
      "end": 49.36,
      "type": "word"
    },
    {
      "text": " ",
      "start": 49.36,
      "end": 49.36,
      "type": "spacing"
    },
    {
      "text": "okrášlene",
      "start": 49.36,
      "end": 50.039,
      "type": "word"
    },
    {
      "text": " ",
      "start": 50.039,
      "end": 50.059,
      "type": "spacing"
    },
    {
      "text": "zlatými",
      "start": 50.059,
      "end": 50.52,
      "type": "word"
    },
    {
      "text": " ",
      "start": 50.52,
      "end": 50.779,
      "type": "spacing"
    },
    {
      "text": "perami,",
      "start": 50.779,
      "end": 51.379,
      "type": "word"
    },
    {
      "text": " ",
      "start": 51.379,
      "end": 51.399,
      "type": "spacing"
    },
    {
      "text": "perlami",
      "start": 51.399,
      "end": 51.899,
      "type": "word"
    },
    {
      "text": " ",
      "start": 51.899,
      "end": 51.899,
      "type": "spacing"
    },
    {
      "text": "a...",
      "start": 51.899,
      "end": 52.059,
      "type": "word"
    },
    {
      "text": " ",
      "start": 52.059,
      "end": 52.739,
      "type": "spacing"
    },
    {
      "text": "Počkaj,",
      "start": 52.739,
      "end": 53.119,
      "type": "word"
    },
    {
      "text": " ",
      "start": 53.119,
      "end": 53.119,
      "type": "spacing"
    },
    {
      "text": "ale",
      "start": 53.119,
      "end": 53.279,
      "type": "word"
    },
    {
      "text": " ",
      "start": 53.279,
      "end": 53.279,
      "type": "spacing"
    },
    {
      "text": "ten",
      "start": 53.279,
      "end": 53.459,
      "type": "word"
    },
    {
      "text": " ",
      "start": 53.459,
      "end": 53.479,
      "type": "spacing"
    },
    {
      "text": "idealizovaný",
      "start": 53.479,
      "end": 54.299,
      "type": "word"
    },
    {
      "text": " ",
      "start": 54.299,
      "end": 54.299,
      "type": "spacing"
    },
    {
      "text": "je",
      "start": 54.299,
      "end": 54.439,
      "type": "word"
    },
    {
      "text": " ",
      "start": 54.439,
      "end": 54.439,
      "type": "spacing"
    },
    {
      "text": "tu",
      "start": 54.439,
      "end": 54.559,
      "type": "word"
    },
    {
      "text": " ",
      "start": 54.559,
      "end": 54.579,
      "type": "spacing"
    },
    {
      "text": "kto?",
      "start": 54.579,
      "end": 54.919,
      "type": "word"
    },
    {
      "text": " ",
      "start": 54.919,
      "end": 56.259,
      "type": "spacing"
    },
    {
      "text": "To",
      "start": 56.259,
      "end": 56.439,
      "type": "word"
    },
    {
      "text": " ",
      "start": 56.439,
      "end": 56.439,
      "type": "spacing"
    },
    {
      "text": "dieťa,",
      "start": 56.439,
      "end": 56.939,
      "type": "word"
    },
    {
      "text": " ",
      "start": 56.939,
      "end": 56.959,
      "type": "spacing"
    },
    {
      "text": "ten",
      "start": 56.959,
      "end": 57.119,
      "type": "word"
    },
    {
      "text": " ",
      "start": 57.119,
      "end": 57.18,
      "type": "spacing"
    },
    {
      "text": "Konštantín.",
      "start": 57.18,
      "end": 58.059,
      "type": "word"
    },
    {
      "text": " ",
      "start": 58.059,
      "end": 58.139,
      "type": "spacing"
    },
    {
      "text": "Čo",
      "start": 58.139,
      "end": 58.299,
      "type": "word"
    },
    {
      "text": " ",
      "start": 58.299,
      "end": 58.319,
      "type": "spacing"
    },
    {
      "text": "je",
      "start": 58.319,
      "end": 58.42,
      "type": "word"
    },
    {
      "text": " ",
      "start": 58.42,
      "end": 58.5,
      "type": "spacing"
    },
    {
      "text": "tu",
      "start": 58.5,
      "end": 58.619,
      "type": "word"
    },
    {
      "text": " ",
      "start": 58.619,
      "end": 58.619,
      "type": "spacing"
    },
    {
      "text": "vlastne",
      "start": 58.619,
      "end": 59.08,
      "type": "word"
    },
    {
      "text": " ",
      "start": 59.08,
      "end": 59.099,
      "type": "spacing"
    },
    {
      "text": "také",
      "start": 59.099,
      "end": 59.439,
      "type": "word"
    },
    {
      "text": " ",
      "start": 59.439,
      "end": 59.439,
      "type": "spacing"
    },
    {
      "text": "vzorové?",
      "start": 59.439,
      "end": 60.339,
      "type": "word"
    },
    {
      "text": " ",
      "start": 60.339,
      "end": 61.119,
      "type": "spacing"
    },
    {
      "text": "Vynikal",
      "start": 61.119,
      "end": 61.419,
      "type": "word"
    },
    {
      "text": " ",
      "start": 61.419,
      "end": 61.419,
      "type": "spacing"
    },
    {
      "text": "veľmi",
      "start": 61.419,
      "end": 61.659,
      "type": "word"
    },
    {
      "text": " ",
      "start": 61.659,
      "end": 61.659,
      "type": "spacing"
    },
    {
      "text": "bystrou",
      "start": 61.659,
      "end": 61.959,
      "type": "word"
    },
    {
      "text": " ",
      "start": 61.959,
      "end": 61.959,
      "type": "spacing"
    },
    {
      "text": "pamäťou.",
      "start": 61.959,
      "end": 62.519,
      "type": "word"
    },
    {
      "text": " ",
      "start": 62.519,
      "end": 62.919,
      "type": "spacing"
    },
    {
      "text": "Všetci",
      "start": 62.919,
      "end": 63.059,
      "type": "word"
    },
    {
      "text": " ",
      "start": 63.059,
      "end": 63.059,
      "type": "spacing"
    },
    {
      "text": "sa",
      "start": 63.059,
      "end": 63.199,
      "type": "word"
    },
    {
      "text": " ",
      "start": 63.199,
      "end": 63.199,
      "type": "spacing"
    },
    {
      "text": "čudovali.",
      "start": 63.199,
      "end": 63.739,
      "type": "word"
    },
    {
      "text": " ",
      "start": 63.739,
      "end": 63.779,
      "type": "spacing"
    },
    {
      "text": "Áno,",
      "start": 63.779,
      "end": 64.219,
      "type": "word"
    },
    {
      "text": " ",
      "start": 64.219,
      "end": 64.239,
      "type": "spacing"
    },
    {
      "text": "aký",
      "start": 64.239,
      "end": 64.479,
      "type": "word"
    },
    {
      "text": " ",
      "start": 64.479,
      "end": 64.499,
      "type": "spacing"
    },
    {
      "text": "bol",
      "start": 64.499,
      "end": 64.699,
      "type": "word"
    },
    {
      "text": " ",
      "start": 64.699,
      "end": 64.759,
      "type": "spacing"
    },
    {
      "text": "úžasný?",
      "start": 64.759,
      "end": 65.399,
      "type": "word"
    },
    {
      "text": " ",
      "start": 65.399,
      "end": 65.399,
      "type": "spacing"
    },
    {
      "text": "Bystrou",
      "start": 65.399,
      "end": 65.779,
      "type": "word"
    },
    {
      "text": " ",
      "start": 65.779,
      "end": 65.899,
      "type": "spacing"
    },
    {
      "text": "pamäťou,",
      "start": 65.899,
      "end": 66.819,
      "type": "word"
    },
    {
      "text": " ",
      "start": 66.819,
      "end": 67.559,
      "type": "spacing"
    },
    {
      "text": "svojím",
      "start": 67.559,
      "end": 67.959,
      "type": "word"
    },
    {
      "text": " ",
      "start": 67.959,
      "end": 67.979,
      "type": "spacing"
    },
    {
      "text": "naozaj,",
      "start": 67.979,
      "end": 68.439,
      "type": "word"
    },
    {
      "text": " ",
      "start": 68.439,
      "end": 68.439,
      "type": "spacing"
    },
    {
      "text": "tým",
      "start": 68.439,
      "end": 68.579,
      "type": "word"
    },
    {
      "text": " ",
      "start": 68.579,
      "end": 68.679,
      "type": "spacing"
    },
    {
      "text": "účenosťou",
      "start": 68.679,
      "end": 69.499,
      "type": "word"
    },
    {
      "text": " ",
      "start": 69.499,
      "end": 69.519,
      "type": "spacing"
    },
    {
      "text": "ako",
      "start": 69.519,
      "end": 69.799,
      "type": "word"
    },
    {
      "text": " ",
      "start": 69.799,
      "end": 69.799,
      "type": "spacing"
    },
    {
      "text": "vynikal.",
      "start": 69.799,
      "end": 70.619,
      "type": "word"
    },
    {
      "text": " ",
      "start": 70.619,
      "end": 70.979,
      "type": "spacing"
    },
    {
      "text": "A",
      "start": 70.979,
      "end": 71.119,
      "type": "word"
    },
    {
      "text": " ",
      "start": 71.119,
      "end": 71.139,
      "type": "spacing"
    },
    {
      "text": "čím",
      "start": 71.139,
      "end": 71.339,
      "type": "word"
    },
    {
      "text": " ",
      "start": 71.339,
      "end": 71.399,
      "type": "spacing"
    },
    {
      "text": "to",
      "start": 71.399,
      "end": 71.519,
      "type": "word"
    },
    {
      "text": " ",
      "start": 71.519,
      "end": 71.559,
      "type": "spacing"
    },
    {
      "text": "bolo",
      "start": 71.559,
      "end": 71.819,
      "type": "word"
    },
    {
      "text": " ",
      "start": 71.819,
      "end": 71.839,
      "type": "spacing"
    },
    {
      "text": "dané?",
      "start": 71.839,
      "end": 72.179,
      "type": "word"
    },
    {
      "text": " ",
      "start": 72.179,
      "end": 72.179,
      "type": "spacing"
    },
    {
      "text": "Lebo",
      "start": 72.179,
      "end": 72.419,
      "type": "word"
    },
    {
      "text": " ",
      "start": 72.419,
      "end": 72.459,
      "type": "spacing"
    },
    {
      "text": "čo",
      "start": 72.459,
      "end": 72.619,
      "type": "word"
    },
    {
      "text": " ",
      "start": 72.619,
      "end": 72.659,
      "type": "spacing"
    },
    {
      "text": "si",
      "start": 72.659,
      "end": 72.799,
      "type": "word"
    },
    {
      "text": " ",
      "start": 72.799,
      "end": 72.839,
      "type": "spacing"
    },
    {
      "text": "vybral",
      "start": 72.839,
      "end": 73.279,
      "type": "word"
    },
    {
      "text": " ",
      "start": 73.279,
      "end": 73.339,
      "type": "spacing"
    },
    {
      "text": "za",
      "start": 73.339,
      "end": 73.499,
      "type": "word"
    },
    {
      "text": " ",
      "start": 73.499,
      "end": 73.519,
      "type": "spacing"
    },
    {
      "text": "celoživotnú",
      "start": 73.519,
      "end": 74.219,
      "type": "word"
    },
    {
      "text": " ",
      "start": 74.219,
      "end": 74.239,
      "type": "spacing"
    },
    {
      "text": "spoločníčku?",
      "start": 74.239,
      "end": 75.259,
      "type": "word"
    },
    {
      "text": " ",
      "start": 75.259,
      "end": 75.459,
      "type": "spacing"
    },
    {
      "text": "Koho?",
      "start": 75.459,
      "end": 75.939,
      "type": "word"
    },
    {
      "text": " ",
      "start": 75.939,
      "end": 76.039,
      "type": "spacing"
    },
    {
      "text": "Svoju",
      "start": 76.039,
      "end": 76.199,
      "type": "word"
    },
    {
      "text": " ",
      "start": 76.199,
      "end": 76.239,
      "type": "spacing"
    },
    {
      "text": "sestru.",
      "start": 76.239,
      "end": 76.799,
      "type": "word"
    },
    {
      "text": " ",
      "start": 76.799,
      "end": 77.279,
      "type": "spacing"
    },
    {
      "text": "Múdrosť",
      "start": 77.279,
      "end": 78.259,
      "type": "word"
    },
    {
      "text": " ",
      "start": 78.259,
      "end": 78.279,
      "type": "spacing"
    },
    {
      "text": "si",
      "start": 78.279,
      "end": 78.459,
      "type": "word"
    },
    {
      "text": " ",
      "start": 78.459,
      "end": 78.499,
      "type": "spacing"
    },
    {
      "text": "vybral.",
      "start": 78.499,
      "end": 79.179,
      "type": "word"
    },
    {
      "text": " ",
      "start": 79.179,
      "end": 79.419,
      "type": "spacing"
    },
    {
      "text": "Sofiu,",
      "start": 79.419,
      "end": 80.019,
      "type": "word"
    },
    {
      "text": " ",
      "start": 80.019,
      "end": 80.839,
      "type": "spacing"
    },
    {
      "text": "svoju",
      "start": 80.839,
      "end": 81.179,
      "type": "word"
    },
    {
      "text": " ",
      "start": 81.179,
      "end": 81.259,
      "type": "spacing"
    },
    {
      "text": "sestru.",
      "start": 81.259,
      "end": 81.959,
      "type": "word"
    },
    {
      "text": " ",
      "start": 81.959,
      "end": 82.459,
      "type": "spacing"
    },
    {
      "text": "Ty",
      "start": 82.459,
      "end": 82.599,
      "type": "word"
    },
    {
      "text": " ",
      "start": 82.599,
      "end": 82.599,
      "type": "spacing"
    },
    {
      "text": "si",
      "start": 82.599,
      "end": 82.759,
      "type": "word"
    },
    {
      "text": " ",
      "start": 82.759,
      "end": 82.759,
      "type": "spacing"
    },
    {
      "text": "mimo.",
      "start": 82.759,
      "end": 83.099,
      "type": "word"
    },
    {
      "text": " ",
      "start": 83.099,
      "end": 83.099,
      "type": "spacing"
    },
    {
      "text": "Ty",
      "start": 83.099,
      "end": 83.199,
      "type": "word"
    },
    {
      "text": " ",
      "start": 83.199,
      "end": 83.219,
      "type": "spacing"
    },
    {
      "text": "si",
      "start": 83.219,
      "end": 83.359,
      "type": "word"
    },
    {
      "text": " ",
      "start": 83.359,
      "end": 83.359,
      "type": "spacing"
    },
    {
      "text": "zas",
      "start": 83.359,
      "end": 83.599,
      "type": "word"
    },
    {
      "text": " ",
      "start": 83.599,
      "end": 83.619,
      "type": "spacing"
    },
    {
      "text": "v",
      "start": 83.619,
      "end": 83.699,
      "type": "word"
    },
    {
      "text": " ",
      "start": 83.699,
      "end": 83.719,
      "type": "spacing"
    },
    {
      "text": "Oha!",
      "start": 83.719,
      "end": 84.019,
      "type": "word"
    },
    {
      "text": " ",
      "start": 84.019,
      "end": 84.879,
      "type": "spacing"
    },
    {
      "text": "Si",
      "start": 84.879,
      "end": 84.979,
      "type": "word"
    },
    {
      "text": " ",
      "start": 84.979,
      "end": 85.519,
      "type": "spacing"
    },
    {
      "text": "malá",
      "start": 85.519,
      "end": 85.719,
      "type": "word"
    },
    {
      "text": " ",
      "start": 85.719,
      "end": 85.759,
      "type": "spacing"
    },
    {
      "text": "babka",
      "start": 85.759,
      "end": 85.859,
      "type": "word"
    },
    {
      "text": " ",
      "start": 85.859,
      "end": 85.879,
      "type": "spacing"
    },
    {
      "text": "nadavka.",
      "start": 85.879,
      "end": 86.559,
      "type": "word"
    },
    {
      "text": " ",
      "start": 86.559,
      "end": 87.939,
      "type": "spacing"
    },
    {
      "text": "Rozhlas",
      "start": 87.939,
      "end": 88.399,
      "type": "word"
    },
    {
      "text": " ",
      "start": 88.399,
      "end": 88.439,
      "type": "spacing"
    },
    {
      "text": "stredovekej",
      "start": 88.439,
      "end": 88.979,
      "type": "word"
    },
    {
      "text": " ",
      "start": 88.979,
      "end": 88.999,
      "type": "spacing"
    },
    {
      "text": "literatúry",
      "start": 88.999,
      "end": 89.599,
      "type": "word"
    },
    {
      "text": " ",
      "start": 89.599,
      "end": 89.599,
      "type": "spacing"
    },
    {
      "text": "na",
      "start": 89.599,
      "end": 89.779,
      "type": "word"
    },
    {
      "text": " ",
      "start": 89.779,
      "end": 89.839,
      "type": "spacing"
    },
    {
      "text": "Slovensku.",
      "start": 89.839,
      "end": 90.479,
      "type": "word"
    },
    {
      "text": " ",
      "start": 90.479,
      "end": 90.499,
      "type": "spacing"
    },
    {
      "text": "Naozaj",
      "start": 90.499,
      "end": 91.139,
      "type": "word"
    },
    {
      "text": " ",
      "start": 91.139,
      "end": 91.339,
      "type": "spacing"
    },
    {
      "text": "súvislosti",
      "start": 91.339,
      "end": 92.039,
      "type": "word"
    },
    {
      "text": " ",
      "start": 92.039,
      "end": 92.059,
      "type": "spacing"
    },
    {
      "text": "týkajúce",
      "start": 92.059,
      "end": 92.599,
      "type": "word"
    },
    {
      "text": " ",
      "start": 92.599,
      "end": 92.619,
      "type": "spacing"
    },
    {
      "text": "sa",
      "start": 92.619,
      "end": 92.819,
      "type": "word"
    },
    {
      "text": " ",
      "start": 92.819,
      "end": 92.819,
      "type": "spacing"
    },
    {
      "text": "Konštantína",
      "start": 92.819,
      "end": 93.339,
      "type": "word"
    },
    {
      "text": " ",
      "start": 93.339,
      "end": 93.839,
      "type": "spacing"
    },
    {
      "text": "tej",
      "start": 93.839,
      "end": 94.019,
      "type": "word"
    },
    {
      "text": " ",
      "start": 94.019,
      "end": 94.199,
      "type": "spacing"
    },
    {
      "text": "byzantskej",
      "start": 94.199,
      "end": 95.019,
      "type": "word"
    },
    {
      "text": " ",
      "start": 95.019,
      "end": 95.079,
      "type": "spacing"
    },
    {
      "text": "misie?",
      "start": 95.079,
      "end": 95.759,
      "type": "word"
    },
    {
      "text": " ",
      "start": 95.759,
      "end": 96.299,
      "type": "spacing"
    },
    {
      "text": "Významnosť",
      "start": 96.299,
      "end": 96.879,
      "type": "word"
    },
    {
      "text": " ",
      "start": 96.879,
      "end": 96.899,
      "type": "spacing"
    },
    {
      "text": "osobnosti",
      "start": 96.899,
      "end": 97.399,
      "type": "word"
    },
    {
      "text": " ",
      "start": 97.399,
      "end": 97.419,
      "type": "spacing"
    },
    {
      "text": "označenej",
      "start": 97.419,
      "end": 97.939,
      "type": "word"
    },
    {
      "text": " ",
      "start": 97.939,
      "end": 97.939,
      "type": "spacing"
    },
    {
      "text": "ako",
      "start": 97.939,
      "end": 98.139,
      "type": "word"
    },
    {
      "text": " ",
      "start": 98.139,
      "end": 98.199,
      "type": "spacing"
    },
    {
      "text": "filozof",
      "start": 98.199,
      "end": 98.879,
      "type": "word"
    },
    {
      "text": " ",
      "start": 98.879,
      "end": 98.899,
      "type": "spacing"
    },
    {
      "text": "počiatkov",
      "start": 98.899,
      "end": 99.459,
      "type": "word"
    },
    {
      "text": " ",
      "start": 99.459,
      "end": 99.459,
      "type": "spacing"
    },
    {
      "text": "stredovekej",
      "start": 99.459,
      "end": 100.039,
      "type": "word"
    },
    {
      "text": " ",
      "start": 100.039,
      "end": 100.039,
      "type": "spacing"
    },
    {
      "text": "literatúry.",
      "start": 100.039,
      "end": 100.899,
      "type": "word"
    },
    {
      "text": " ",
      "start": 100.899,
      "end": 101.319,
      "type": "spacing"
    },
    {
      "text": "Konštantín",
      "start": 101.319,
      "end": 103.779,
      "type": "word"
    },
    {
      "text": " ",
      "start": 103.779,
      "end": 103.959,
      "type": "spacing"
    },
    {
      "text": "je",
      "start": 103.959,
      "end": 104.139,
      "type": "word"
    },
    {
      "text": " ",
      "start": 104.139,
      "end": 104.179,
      "type": "spacing"
    },
    {
      "text": "to",
      "start": 104.179,
      "end": 104.419,
      "type": "word"
    },
    {
      "text": " ",
      "start": 104.419,
      "end": 105.979,
      "type": "spacing"
    },
    {
      "text": "šíriteľ",
      "start": 105.979,
      "end": 106.479,
      "type": "word"
    },
    {
      "text": " ",
      "start": 106.479,
      "end": 106.539,
      "type": "spacing"
    },
    {
      "text": "kresťanstva,",
      "start": 106.539,
      "end": 107.539,
      "type": "word"
    },
    {
      "text": " ",
      "start": 107.539,
      "end": 107.659,
      "type": "spacing"
    },
    {
      "text": "zostavovateľ",
      "start": 107.659,
      "end": 108.579,
      "type": "word"
    },
    {
      "text": " ",
      "start": 108.579,
      "end": 108.659,
      "type": "spacing"
    },
    {
      "text": "písma,",
      "start": 108.659,
      "end": 109.319,
      "type": "word"
    },
    {
      "text": " ",
      "start": 109.319,
      "end": 109.599,
      "type": "spacing"
    },
    {
      "text": "prekladateľ",
      "start": 109.599,
      "end": 110.439,
      "type": "word"
    },
    {
      "text": " ",
      "start": 110.439,
      "end": 110.499,
      "type": "spacing"
    },
    {
      "text": "prvých",
      "start": 110.499,
      "end": 110.839,
      "type": "word"
    },
    {
      "text": " ",
      "start": 110.839,
      "end": 110.919,
      "type": "spacing"
    },
    {
      "text": "textov",
      "start": 110.919,
      "end": 111.439,
      "type": "word"
    },
    {
      "text": " ",
      "start": 111.439,
      "end": 111.459,
      "type": "spacing"
    },
    {
      "text": "a",
      "start": 111.459,
      "end": 111.559,
      "type": "word"
    },
    {
      "text": " ",
      "start": 111.559,
      "end": 111.659,
      "type": "spacing"
    },
    {
      "text": "autor",
      "start": 111.659,
      "end": 112.079,
      "type": "word"
    },
    {
      "text": " ",
      "start": 112.079,
      "end": 112.139,
      "type": "spacing"
    },
    {
      "text": "prvej",
      "start": 112.139,
      "end": 112.599,
      "type": "word"
    },
    {
      "text": " ",
      "start": 112.599,
      "end": 113.259,
      "type": "spacing"
    },
    {
      "text": "básne.",
      "start": 113.259,
      "end": 113.959,
      "type": "word"
    },
    {
      "text": " ",
      "start": 113.959,
      "end": 113.959,
      "type": "spacing"
    },
    {
      "text": "Ešte",
      "start": 113.959,
      "end": 114.259,
      "type": "word"
    },
    {
      "text": " ",
      "start": 114.259,
      "end": 114.259,
      "type": "spacing"
    },
    {
      "text": "niečo",
      "start": 114.259,
      "end": 114.579,
      "type": "word"
    },
    {
      "text": " ",
      "start": 114.579,
      "end": 114.579,
      "type": "spacing"
    },
    {
      "text": "významné",
      "start": 114.579,
      "end": 115.099,
      "type": "word"
    },
    {
      "text": " ",
      "start": 115.099,
      "end": 115.099,
      "type": "spacing"
    },
    {
      "text": "spravil?",
      "start": 115.099,
      "end": 115.819,
      "type": "word"
    },
    {
      "text": " ",
      "start": 115.819,
      "end": 116.379,
      "type": "spacing"
    },
    {
      "text": "Že",
      "start": 116.379,
      "end": 116.519,
      "type": "word"
    },
    {
      "text": " ",
      "start": 116.519,
      "end": 116.559,
      "type": "spacing"
    },
    {
      "text": "staroslovienčinu",
      "start": 116.559,
      "end": 117.539,
      "type": "word"
    },
    {
      "text": " ",
      "start": 117.539,
      "end": 117.539,
      "type": "spacing"
    },
    {
      "text": "ako",
      "start": 117.539,
      "end": 117.779,
      "type": "word"
    },
    {
      "text": " ",
      "start": 117.779,
      "end": 117.779,
      "type": "spacing"
    },
    {
      "text": "liturgický",
      "start": 117.779,
      "end": 118.419,
      "type": "word"
    },
    {
      "text": " ",
      "start": 118.419,
      "end": 118.459,
      "type": "spacing"
    },
    {
      "text": "jazyk",
      "start": 118.459,
      "end": 118.959,
      "type": "word"
    },
    {
      "text": " ",
      "start": 118.959,
      "end": 119.079,
      "type": "spacing"
    },
    {
      "text": "obhajoval",
      "start": 119.079,
      "end": 119.819,
      "type": "word"
    },
    {
      "text": " ",
      "start": 119.819,
      "end": 119.859,
      "type": "spacing"
    },
    {
      "text": "a",
      "start": 119.859,
      "end": 119.959,
      "type": "word"
    },
    {
      "text": " ",
      "start": 119.959,
      "end": 119.959,
      "type": "spacing"
    },
    {
      "text": "dokonca",
      "start": 119.959,
      "end": 120.419,
      "type": "word"
    },
    {
      "text": " ",
      "start": 120.419,
      "end": 120.439,
      "type": "spacing"
    },
    {
      "text": "dosiahol",
      "start": 120.439,
      "end": 120.979,
      "type": "word"
    },
    {
      "text": " ",
      "start": 120.979,
      "end": 121.039,
      "type": "spacing"
    },
    {
      "text": "jej",
      "start": 121.039,
      "end": 121.299,
      "type": "word"
    },
    {
      "text": " ",
      "start": 121.299,
      "end": 121.799,
      "type": "spacing"
    },
    {
      "text": "schválenie?",
      "start": 121.799,
      "end": 122.699,
      "type": "word"
    },
    {
      "text": " ",
      "start": 122.699,
      "end": 122.719,
      "type": "spacing"
    },
    {
      "text": "Čiže",
      "start": 122.719,
      "end": 122.959,
      "type": "word"
    },
    {
      "text": " ",
      "start": 122.959,
      "end": 122.979,
      "type": "spacing"
    },
    {
      "text": "vediete",
      "start": 122.979,
      "end": 123.439,
      "type": "word"
    },
    {
      "text": " ",
      "start": 123.439,
      "end": 123.499,
      "type": "spacing"
    },
    {
      "text": "aj",
      "start": 123.499,
      "end": 123.559,
      "type": "word"
    },
    {
      "text": " ",
      "start": 123.559,
      "end": 123.619,
      "type": "spacing"
    },
    {
      "text": "význam",
      "start": 123.619,
      "end": 124.039,
      "type": "word"
    },
    {
      "text": " ",
      "start": 124.039,
      "end": 124.039,
      "type": "spacing"
    },
    {
      "text": "Konštantína.",
      "start": 124.039,
      "end": 125.079,
      "type": "word"
    },
    {
      "text": " ",
      "start": 125.079,
      "end": 126.259,
      "type": "spacing"
    },
    {
      "text": "Legendu",
      "start": 126.259,
      "end": 126.739,
      "type": "word"
    },
    {
      "text": " ",
      "start": 126.739,
      "end": 126.739,
      "type": "spacing"
    },
    {
      "text": "sme",
      "start": 126.739,
      "end": 126.939,
      "type": "word"
    },
    {
      "text": " ",
      "start": 126.939,
      "end": 126.999,
      "type": "spacing"
    },
    {
      "text": "spomínali.",
      "start": 126.999,
      "end": 127.879,
      "type": "word"
    },
    {
      "text": " ",
      "start": 127.879,
      "end": 129.059,
      "type": "spacing"
    },
    {
      "text": "Všimnite",
      "start": 129.059,
      "end": 129.599,
      "type": "word"
    },
    {
      "text": " ",
      "start": 129.599,
      "end": 129.659,
      "type": "spacing"
    },
    {
      "text": "si",
      "start": 129.659,
      "end": 129.959,
      "type": "word"
    },
    {
      "text": " ",
      "start": 129.959,
      "end": 130.479,
      "type": "spacing"
    },
    {
      "text": "potom",
      "start": 130.479,
      "end": 131.079,
      "type": "word"
    },
    {
      "text": " ",
      "start": 131.079,
      "end": 131.099,
      "type": "spacing"
    },
    {
      "text": "tie",
      "start": 131.099,
      "end": 131.259,
      "type": "word"
    },
    {
      "text": " ",
      "start": 131.259,
      "end": 131.279,
      "type": "spacing"
    },
    {
      "text": "otázky",
      "start": 131.279,
      "end": 131.799,
      "type": "word"
    },
    {
      "text": " ",
      "start": 131.799,
      "end": 131.819,
      "type": "spacing"
    },
    {
      "text": "štyri,",
      "start": 131.819,
      "end": 132.179,
      "type": "word"
    },
    {
      "text": " ",
      "start": 132.179,
      "end": 132.239,
      "type": "spacing"
    },
    {
      "text": "päť,",
      "start": 132.239,
      "end": 132.499,
      "type": "word"
    },
    {
      "text": " ",
      "start": 132.499,
      "end": 132.599,
      "type": "spacing"
    },
    {
      "text": "šesť.",
      "start": 132.599,
      "end": 133.239,
      "type": "word"
    },
    {
      "text": " ",
      "start": 133.239,
      "end": 135.219,
      "type": "spacing"
    },
    {
      "text": "Presne",
      "start": 135.219,
      "end": 135.579,
      "type": "word"
    },
    {
      "text": " ",
      "start": 135.579,
      "end": 135.579,
      "type": "spacing"
    },
    {
      "text": "preto,",
      "start": 135.579,
      "end": 135.679,
      "type": "word"
    },
    {
      "text": " ",
      "start": 135.679,
      "end": 135.699,
      "type": "spacing"
    },
    {
      "text": "že...",
      "start": 135.699,
      "end": 136.179,
      "type": "word"
    },
    {
      "text": " ",
      "start": 136.179,
      "end": 136.179,
      "type": "spacing"
    },
    {
      "text": "Máte",
      "start": 136.179,
      "end": 136.519,
      "type": "word"
    },
    {
      "text": " ",
      "start": 136.519,
      "end": 136.539,
      "type": "spacing"
    },
    {
      "text": "tam",
      "start": 136.539,
      "end": 136.699,
      "type": "word"
    },
    {
      "text": " ",
      "start": 136.699,
      "end": 136.739,
      "type": "spacing"
    },
    {
      "text": "to",
      "start": 136.739,
      "end": 136.839,
      "type": "word"
    },
    {
      "text": " ",
      "start": 136.839,
      "end": 136.839,
      "type": "spacing"
    },
    {
      "text": "štristické",
      "start": 136.839,
      "end": 137.479,
      "type": "word"
    },
    {
      "text": " ",
      "start": 137.479,
      "end": 137.499,
      "type": "spacing"
    },
    {
      "text": "využitie.",
      "start": 137.499,
      "end": 138.219,
      "type": "word"
    },
    {
      "text": " ",
      "start": 138.219,
      "end": 138.359,
      "type": "spacing"
    },
    {
      "text": "Ako",
      "start": 138.359,
      "end": 138.619,
      "type": "word"
    },
    {
      "text": " ",
      "start": 138.619,
      "end": 138.679,
      "type": "spacing"
    },
    {
      "text": "to",
      "start": 138.679,
      "end": 138.799,
      "type": "word"
    },
    {
      "text": " ",
      "start": 138.799,
      "end": 138.799,
      "type": "spacing"
    },
    {
      "text": "vlastne",
      "start": 138.799,
      "end": 139.239,
      "type": "word"
    },
    {
      "text": " ",
      "start": 139.239,
      "end": 139.239,
      "type": "spacing"
    },
    {
      "text": "vieme",
      "start": 139.239,
      "end": 139.539,
      "type": "word"
    },
    {
      "text": " ",
      "start": 139.539,
      "end": 139.559,
      "type": "spacing"
    },
    {
      "text": "využiť?",
      "start": 139.559,
      "end": 140.079,
      "type": "word"
    },
    {
      "text": " ",
      "start": 140.079,
      "end": 140.119,
      "type": "spacing"
    },
    {
      "text": "Čo",
      "start": 140.119,
      "end": 140.239,
      "type": "word"
    },
    {
      "text": " ",
      "start": 140.239,
      "end": 140.299,
      "type": "spacing"
    },
    {
      "text": "je",
      "start": 140.299,
      "end": 140.399,
      "type": "word"
    },
    {
      "text": " ",
      "start": 140.399,
      "end": 140.439,
      "type": "spacing"
    },
    {
      "text": "to",
      "start": 140.439,
      "end": 140.539,
      "type": "word"
    },
    {
      "text": " ",
      "start": 140.539,
      "end": 140.539,
      "type": "spacing"
    },
    {
      "text": "pre",
      "start": 140.539,
      "end": 140.719,
      "type": "word"
    },
    {
      "text": " ",
      "start": 140.719,
      "end": 140.719,
      "type": "spacing"
    },
    {
      "text": "nás?",
      "start": 140.719,
      "end": 140.939,
      "type": "word"
    },
    {
      "text": " ",
      "start": 140.939,
      "end": 141.099,
      "type": "spacing"
    },
    {
      "text": "V",
      "start": 141.099,
      "end": 141.179,
      "type": "word"
    },
    {
      "text": " ",
      "start": 141.179,
      "end": 141.179,
      "type": "spacing"
    },
    {
      "text": "čom",
      "start": 141.179,
      "end": 141.339,
      "type": "word"
    },
    {
      "text": " ",
      "start": 141.339,
      "end": 141.359,
      "type": "spacing"
    },
    {
      "text": "je",
      "start": 141.359,
      "end": 141.459,
      "type": "word"
    },
    {
      "text": " ",
      "start": 141.459,
      "end": 141.459,
      "type": "spacing"
    },
    {
      "text": "to",
      "start": 141.459,
      "end": 141.559,
      "type": "word"
    },
    {
      "text": " ",
      "start": 141.559,
      "end": 141.579,
      "type": "spacing"
    },
    {
      "text": "zaujímavé?",
      "start": 141.579,
      "end": 142.179,
      "type": "word"
    },
    {
      "text": " ",
      "start": 142.179,
      "end": 142.719,
      "type": "spacing"
    },
    {
      "text": "Vyhľadaj",
      "start": 142.719,
      "end": 143.199,
      "type": "word"
    },
    {
      "text": " ",
      "start": 143.199,
      "end": 143.199,
      "type": "spacing"
    },
    {
      "text": "v",
      "start": 143.199,
      "end": 143.239,
      "type": "word"
    },
    {
      "text": " ",
      "start": 143.239,
      "end": 143.239,
      "type": "spacing"
    },
    {
      "text": "texte",
      "start": 143.239,
      "end": 143.579,
      "type": "word"
    },
    {
      "text": " ",
      "start": 143.579,
      "end": 143.599,
      "type": "spacing"
    },
    {
      "text": "synonymá",
      "start": 143.599,
      "end": 144.119,
      "type": "word"
    },
    {
      "text": " ",
      "start": 144.119,
      "end": 144.119,
      "type": "spacing"
    },
    {
      "text": "slova",
      "start": 144.119,
      "end": 144.899,
      "type": "word"
    },
    {
      "text": " ",
      "start": 144.899,
      "end": 144.939,
      "type": "spacing"
    },
    {
      "text": "slovesa",
      "start": 144.939,
      "end": 145.039,
      "type": "word"
    },
    {
      "text": " ",
      "start": 145.039,
      "end": 145.119,
      "type": "spacing"
    },
    {
      "text": "povedať,",
      "start": 145.119,
      "end": 145.859,
      "type": "word"
    },
    {
      "text": " ",
      "start": 145.859,
      "end": 146.319,
      "type": "spacing"
    },
    {
      "text": "Hovoria.",
      "start": 146.319,
      "end": 146.819,
      "type": "word"
    },
    {
      "text": " ",
      "start": 146.819,
      "end": 149.039,
      "type": "spacing"
    },
    {
      "text": "Rozprávam.",
      "start": 149.039,
      "end": 149.619,
      "type": "word"
    },
    {
      "text": " ",
      "start": 149.619,
      "end": 149.899,
      "type": "spacing"
    },
    {
      "text": "Hovoriac,",
      "start": 149.899,
      "end": 150.619,
      "type": "word"
    },
    {
      "text": " ",
      "start": 150.619,
      "end": 150.699,
      "type": "spacing"
    },
    {
      "text": "že",
      "start": 150.699,
      "end": 150.859,
      "type": "word"
    },
    {
      "text": " ",
      "start": 150.859,
      "end": 150.879,
      "type": "spacing"
    },
    {
      "text": "hovoriť.",
      "start": 150.879,
      "end": 151.639,
      "type": "word"
    },
    {
      "text": " ",
      "start": 151.639,
      "end": 151.999,
      "type": "spacing"
    },
    {
      "text": "Rozprávať.",
      "start": 151.999,
      "end": 152.659,
      "type": "word"
    },
    {
      "text": " ",
      "start": 152.659,
      "end": 152.699,
      "type": "spacing"
    },
    {
      "text": "Rozprávať.",
      "start": 152.699,
      "end": 153.679,
      "type": "word"
    },
    {
      "text": " ",
      "start": 153.679,
      "end": 153.799,
      "type": "spacing"
    },
    {
      "text": "Napríklad.",
      "start": 153.799,
      "end": 154.759,
      "type": "word"
    },
    {
      "text": " ",
      "start": 154.759,
      "end": 155.439,
      "type": "spacing"
    },
    {
      "text": "Toto",
      "start": 155.439,
      "end": 155.719,
      "type": "word"
    },
    {
      "text": " ",
      "start": 155.719,
      "end": 155.779,
      "type": "spacing"
    },
    {
      "text": "sme",
      "start": 155.779,
      "end": 155.979,
      "type": "word"
    },
    {
      "text": " ",
      "start": 155.979,
      "end": 155.999,
      "type": "spacing"
    },
    {
      "text": "vlastne",
      "start": 155.999,
      "end": 156.399,
      "type": "word"
    },
    {
      "text": " ",
      "start": 156.399,
      "end": 156.419,
      "type": "spacing"
    },
    {
      "text": "vytvorili",
      "start": 156.419,
      "end": 156.999,
      "type": "word"
    },
    {
      "text": " ",
      "start": 156.999,
      "end": 156.999,
      "type": "spacing"
    },
    {
      "text": "synonymický",
      "start": 156.999,
      "end": 158.039,
      "type": "word"
    },
    {
      "text": " ",
      "start": 158.039,
      "end": 159.459,
      "type": "spacing"
    },
    {
      "text": "rad",
      "start": 159.459,
      "end": 159.939,
      "type": "word"
    },
    {
      "text": " ",
      "start": 159.939,
      "end": 160.179,
      "type": "spacing"
    },
    {
      "text": "k",
      "start": 160.179,
      "end": 160.259,
      "type": "word"
    },
    {
      "text": " ",
      "start": 160.259,
      "end": 160.259,
      "type": "spacing"
    },
    {
      "text": "tomuto",
      "start": 160.259,
      "end": 160.659,
      "type": "word"
    },
    {
      "text": " ",
      "start": 160.659,
      "end": 160.739,
      "type": "spacing"
    },
    {
      "text": "slovu.",
      "start": 160.739,
      "end": 161.279,
      "type": "word"
    },
    {
      "text": " ",
      "start": 161.279,
      "end": 161.839,
      "type": "spacing"
    },
    {
      "text": "Ešte",
      "start": 161.839,
      "end": 162.159,
      "type": "word"
    },
    {
      "text": " ",
      "start": 162.159,
      "end": 162.179,
      "type": "spacing"
    },
    {
      "text": "niečo?",
      "start": 162.179,
      "end": 162.779,
      "type": "word"
    },
    {
      "text": " ",
      "start": 162.779,
      "end": 163.199,
      "type": "spacing"
    },
    {
      "text": "Pridavné",
      "start": 163.199,
      "end": 163.679,
      "type": "word"
    },
    {
      "text": " ",
      "start": 163.679,
      "end": 163.679,
      "type": "spacing"
    },
    {
      "text": "mená",
      "start": 163.679,
      "end": 163.959,
      "type": "word"
    },
    {
      "text": " ",
      "start": 163.959,
      "end": 163.979,
      "type": "spacing"
    },
    {
      "text": "z",
      "start": 163.979,
      "end": 164.019,
      "type": "word"
    },
    {
      "text": " ",
      "start": 164.019,
      "end": 164.039,
      "type": "spacing"
    },
    {
      "text": "posledného",
      "start": 164.039,
      "end": 164.679,
      "type": "word"
    },
    {
      "text": " ",
      "start": 164.679,
      "end": 164.739,
      "type": "spacing"
    },
    {
      "text": "odseku",
      "start": 164.739,
      "end": 165.199,
      "type": "word"
    },
    {
      "text": " ",
      "start": 165.199,
      "end": 165.199,
      "type": "spacing"
    },
    {
      "text": "vieme",
      "start": 165.199,
      "end": 165.819,
      "type": "word"
    },
    {
      "text": " ",
      "start": 165.819,
      "end": 165.819,
      "type": "spacing"
    },
    {
      "text": "antonymá?",
      "start": 165.819,
      "end": 166.599,
      "type": "word"
    },
    {
      "text": " ",
      "start": 166.599,
      "end": 168.399,
      "type": "spacing"
    },
    {
      "text": "Ako",
      "start": 168.399,
      "end": 168.619,
      "type": "word"
    },
    {
      "text": " ",
      "start": 168.619,
      "end": 168.619,
      "type": "spacing"
    },
    {
      "text": "by",
      "start": 168.619,
      "end": 168.739,
      "type": "word"
    },
    {
      "text": " ",
      "start": 168.739,
      "end": 168.779,
      "type": "spacing"
    },
    {
      "text": "ste",
      "start": 168.779,
      "end": 168.959,
      "type": "word"
    },
    {
      "text": " ",
      "start": 168.959,
      "end": 168.979,
      "type": "spacing"
    },
    {
      "text": "dali,",
      "start": 168.979,
      "end": 169.279,
      "type": "word"
    },
    {
      "text": " ",
      "start": 169.279,
      "end": 169.299,
      "type": "spacing"
    },
    {
      "text": "keď",
      "start": 169.299,
      "end": 169.459,
      "type": "word"
    },
    {
      "text": " ",
      "start": 169.459,
      "end": 169.459,
      "type": "spacing"
    },
    {
      "text": "máme",
      "start": 169.459,
      "end": 169.759,
      "type": "word"
    },
    {
      "text": " ",
      "start": 169.759,
      "end": 169.779,
      "type": "spacing"
    },
    {
      "text": "bystrú",
      "start": 169.779,
      "end": 170.339,
      "type": "word"
    },
    {
      "text": " ",
      "start": 170.339,
      "end": 170.359,
      "type": "spacing"
    },
    {
      "text": "pamäť?",
      "start": 170.359,
      "end": 170.939,
      "type": "word"
    },
    {
      "text": " ",
      "start": 170.939,
      "end": 171.139,
      "type": "spacing"
    },
    {
      "text": "Čo",
      "start": 171.139,
      "end": 171.279,
      "type": "word"
    },
    {
      "text": " ",
      "start": 171.279,
      "end": 171.279,
      "type": "spacing"
    },
    {
      "text": "je",
      "start": 171.279,
      "end": 171.399,
      "type": "word"
    },
    {
      "text": " ",
      "start": 171.399,
      "end": 171.399,
      "type": "spacing"
    },
    {
      "text": "opakom",
      "start": 171.399,
      "end": 171.939,
      "type": "word"
    },
    {
      "text": " ",
      "start": 171.939,
      "end": 171.939,
      "type": "spacing"
    },
    {
      "text": "bystrej",
      "start": 171.939,
      "end": 172.439,
      "type": "word"
    },
    {
      "text": " ",
      "start": 172.439,
      "end": 172.479,
      "type": "spacing"
    },
    {
      "text": "pamäti?",
      "start": 172.479,
      "end": 172.959,
      "type": "word"
    },
    {
      "text": " ",
      "start": 172.959,
      "end": 172.959,
      "type": "spacing"
    },
    {
      "text": "Tupá.",
      "start": 172.959,
      "end": 173.359,
      "type": "word"
    },
    {
      "text": " ",
      "start": 173.359,
      "end": 173.399,
      "type": "spacing"
    },
    {
      "text": "Tupá.",
      "start": 173.399,
      "end": 173.419,
      "type": "word"
    },
    {
      "text": " ",
      "start": 173.419,
      "end": 173.779,
      "type": "spacing"
    },
    {
      "text": "Tupá",
      "start": 173.779,
      "end": 174.699,
      "type": "word"
    },
    {
      "text": " ",
      "start": 174.699,
      "end": 174.819,
      "type": "spacing"
    },
    {
      "text": "pamäť",
      "start": 174.819,
      "end": 175.379,
      "type": "word"
    },
    {
      "text": " ",
      "start": 175.379,
      "end": 175.439,
      "type": "spacing"
    },
    {
      "text": "napríklad.",
      "start": 175.439,
      "end": 176.359,
      "type": "word"
    },
    {
      "text": " ",
      "start": 176.359,
      "end": 176.779,
      "type": "spacing"
    },
    {
      "text": "Potom",
      "start": 176.779,
      "end": 177.179,
      "type": "word"
    },
    {
      "text": " ",
      "start": 177.179,
      "end": 177.199,
      "type": "spacing"
    },
    {
      "text": "tam",
      "start": 177.199,
      "end": 177.439,
      "type": "word"
    },
    {
      "text": " ",
      "start": 177.439,
      "end": 177.459,
      "type": "spacing"
    },
    {
      "text": "máme,",
      "start": 177.459,
      "end": 177.839,
      "type": "word"
    },
    {
      "text": " ",
      "start": 177.839,
      "end": 177.879,
      "type": "spacing"
    },
    {
      "text": "čo",
      "start": 177.879,
      "end": 178.059,
      "type": "word"
    },
    {
      "text": " ",
      "start": 178.059,
      "end": 178.079,
      "type": "spacing"
    },
    {
      "text": "ja",
      "start": 178.079,
      "end": 178.199,
      "type": "word"
    },
    {
      "text": " ",
      "start": 178.199,
      "end": 178.259,
      "type": "spacing"
    },
    {
      "text": "viem,",
      "start": 178.259,
      "end": 178.739,
      "type": "word"
    },
    {
      "text": " ",
      "start": 178.739,
      "end": 179.579,
      "type": "spacing"
    },
    {
      "text": "kde",
      "start": 179.579,
      "end": 179.799,
      "type": "word"
    },
    {
      "text": " ",
      "start": 179.799,
      "end": 179.819,
      "type": "spacing"
    },
    {
      "text": "sme",
      "start": 179.819,
      "end": 179.979,
      "type": "word"
    },
    {
      "text": " ",
      "start": 179.979,
      "end": 180.019,
      "type": "spacing"
    },
    {
      "text": "tam",
      "start": 180.019,
      "end": 180.199,
      "type": "word"
    },
    {
      "text": " ",
      "start": 180.199,
      "end": 180.199,
      "type": "spacing"
    },
    {
      "text": "ešte",
      "start": 180.199,
      "end": 180.439,
      "type": "word"
    },
    {
      "text": " ",
      "start": 180.439,
      "end": 180.439,
      "type": "spacing"
    },
    {
      "text": "mali",
      "start": 180.439,
      "end": 180.639,
      "type": "word"
    },
    {
      "text": " ",
      "start": 180.639,
      "end": 180.639,
      "type": "spacing"
    },
    {
      "text": "aké",
      "start": 180.639,
      "end": 180.919,
      "type": "word"
    },
    {
      "text": " ",
      "start": 180.919,
      "end": 180.939,
      "type": "spacing"
    },
    {
      "text": "prídavné",
      "start": 180.939,
      "end": 181.399,
      "type": "word"
    },
    {
      "text": " ",
      "start": 181.399,
      "end": 181.439,
      "type": "spacing"
    },
    {
      "text": "mená?",
      "start": 181.439,
      "end": 181.859,
      "type": "word"
    },
    {
      "text": " ",
      "start": 181.859,
      "end": 182.019,
      "type": "spacing"
    },
    {
      "text": "Pozemský.",
      "start": 182.019,
      "end": 182.599,
      "type": "word"
    },
    {
      "text": " ",
      "start": 182.599,
      "end": 182.599,
      "type": "spacing"
    },
    {
      "text": "Smutný.",
      "start": 182.599,
      "end": 182.859,
      "type": "word"
    },
    {
      "text": " ",
      "start": 182.859,
      "end": 183.419,
      "type": "spacing"
    },
    {
      "text": "Božie",
      "start": 183.419,
      "end": 183.959,
      "type": "word"
    },
    {
      "text": " ",
      "start": 183.959,
      "end": 183.979,
      "type": "spacing"
    },
    {
      "text": "riadenie.",
      "start": 183.979,
      "end": 184.859,
      "type": "word"
    },
    {
      "text": " ",
      "start": 184.859,
      "end": 184.879,
      "type": "spacing"
    },
    {
      "text": "Čo",
      "start": 184.879,
      "end": 184.999,
      "type": "word"
    },
    {
      "text": " ",
      "start": 184.999,
      "end": 185.059,
      "type": "spacing"
    },
    {
      "text": "by",
      "start": 185.059,
      "end": 185.199,
      "type": "word"
    },
    {
      "text": " ",
      "start": 185.199,
      "end": 185.199,
      "type": "spacing"
    },
    {
      "text": "ste",
      "start": 185.199,
      "end": 185.399,
      "type": "word"
    },
    {
      "text": " ",
      "start": 185.399,
      "end": 185.419,
      "type": "spacing"
    },
    {
      "text": "dali",
      "start": 185.419,
      "end": 185.699,
      "type": "word"
    },
    {
      "text": " ",
      "start": 185.699,
      "end": 185.699,
      "type": "spacing"
    },
    {
      "text": "k",
      "start": 185.699,
      "end": 185.739,
      "type": "word"
    },
    {
      "text": " ",
      "start": 185.739,
      "end": 185.799,
      "type": "spacing"
    },
    {
      "text": "slovu",
      "start": 185.799,
      "end": 186.119,
      "type": "word"
    },
    {
      "text": " ",
      "start": 186.119,
      "end": 186.239,
      "type": "spacing"
    },
    {
      "text": "Božie",
      "start": 186.239,
      "end": 186.759,
      "type": "word"
    },
    {
      "text": " ",
      "start": 186.759,
      "end": 186.859,
      "type": "spacing"
    },
    {
      "text": "ako",
      "start": 186.859,
      "end": 187.199,
      "type": "word"
    },
    {
      "text": " ",
      "start": 187.199,
      "end": 187.419,
      "type": "spacing"
    },
    {
      "text": "antonym?",
      "start": 187.419,
      "end": 187.539,
      "type": "word"
    },
    {
      "text": " ",
      "start": 187.539,
      "end": 187.539,
      "type": "spacing"
    },
    {
      "text": "Ľudske?",
      "start": 187.539,
      "end": 187.699,
      "type": "word"
    },
    {
      "text": " ",
      "start": 187.699,
      "end": 187.699,
      "type": "spacing"
    },
    {
      "text": "Ateistické",
      "start": 187.699,
      "end": 188.679,
      "type": "word"
    },
    {
      "text": " ",
      "start": 188.679,
      "end": 188.839,
      "type": "spacing"
    },
    {
      "text": "riadenie.",
      "start": 188.839,
      "end": 189.419,
      "type": "word"
    },
    {
      "text": " ",
      "start": 189.419,
      "end": 189.459,
      "type": "spacing"
    },
    {
      "text": "Ľudske?",
      "start": 189.459,
      "end": 189.839,
      "type": "word"
    },
    {
      "text": " ",
      "start": 189.839,
      "end": 190.179,
      "type": "spacing"
    },
    {
      "text": "Pekelné",
      "start": 190.179,
      "end": 190.699,
      "type": "word"
    },
    {
      "text": " ",
      "start": 190.699,
      "end": 190.699,
      "type": "spacing"
    },
    {
      "text": "riadenie.",
      "start": 190.699,
      "end": 191.199,
      "type": "word"
    },
    {
      "text": " ",
      "start": 191.199,
      "end": 191.759,
      "type": "spacing"
    },
    {
      "text": "Ľudské",
      "start": 191.759,
      "end": 192.299,
      "type": "word"
    },
    {
      "text": " ",
      "start": 192.299,
      "end": 192.379,
      "type": "spacing"
    },
    {
      "text": "by",
      "start": 192.379,
      "end": 192.499,
      "type": "word"
    },
    {
      "text": " ",
      "start": 192.499,
      "end": 192.539,
      "type": "spacing"
    },
    {
      "text": "sa",
      "start": 192.539,
      "end": 192.719,
      "type": "word"
    },
    {
      "text": " ",
      "start": 192.719,
      "end": 192.719,
      "type": "spacing"
    },
    {
      "text": "dalo",
      "start": 192.719,
      "end": 192.999,
      "type": "word"
    },
    {
      "text": " ",
      "start": 192.999,
      "end": 193.019,
      "type": "spacing"
    },
    {
      "text": "v",
      "start": 193.019,
      "end": 193.059,
      "type": "word"
    },
    {
      "text": " ",
      "start": 193.059,
      "end": 193.059,
      "type": "spacing"
    },
    {
      "text": "istom",
      "start": 193.059,
      "end": 193.279,
      "type": "word"
    },
    {
      "text": " ",
      "start": 193.279,
      "end": 193.459,
      "type": "spacing"
    },
    {
      "text": "kontexte,",
      "start": 193.459,
      "end": 194.159,
      "type": "word"
    },
    {
      "text": " ",
      "start": 194.159,
      "end": 194.179,
      "type": "spacing"
    },
    {
      "text": "v",
      "start": 194.179,
      "end": 194.219,
      "type": "word"
    },
    {
      "text": " ",
      "start": 194.219,
      "end": 194.219,
      "type": "spacing"
    },
    {
      "text": "istom",
      "start": 194.219,
      "end": 194.539,
      "type": "word"
    },
    {
      "text": " ",
      "start": 194.539,
      "end": 194.559,
      "type": "spacing"
    },
    {
      "text": "kontexte",
      "start": 194.559,
      "end": 195.079,
      "type": "word"
    },
    {
      "text": " ",
      "start": 195.079,
      "end": 195.099,
      "type": "spacing"
    },
    {
      "text": "by",
      "start": 195.099,
      "end": 195.199,
      "type": "word"
    },
    {
      "text": " ",
      "start": 195.199,
      "end": 195.239,
      "type": "spacing"
    },
    {
      "text": "sa",
      "start": 195.239,
      "end": 195.399,
      "type": "word"
    },
    {
      "text": " ",
      "start": 195.399,
      "end": 195.419,
      "type": "spacing"
    },
    {
      "text": "dalo",
      "start": 195.419,
      "end": 195.739,
      "type": "word"
    },
    {
      "text": " ",
      "start": 195.739,
      "end": 195.739,
      "type": "spacing"
    },
    {
      "text": "skôr",
      "start": 195.739,
      "end": 196.179,
      "type": "word"
    },
    {
      "text": " ",
      "start": 196.179,
      "end": 196.339,
      "type": "spacing"
    },
    {
      "text": "pekelné,",
      "start": 196.339,
      "end": 196.899,
      "type": "word"
    },
    {
      "text": " ",
      "start": 196.899,
      "end": 196.899,
      "type": "spacing"
    },
    {
      "text": "diabolské.",
      "start": 196.899,
      "end": 198.079,
      "type": "word"
    },
    {
      "text": " ",
      "start": 198.079,
      "end": 199.659,
      "type": "spacing"
    },
    {
      "text": "Aké",
      "start": 199.659,
      "end": 199.959,
      "type": "word"
    },
    {
      "text": " ",
      "start": 199.959,
      "end": 199.979,
      "type": "spacing"
    },
    {
      "text": "je",
      "start": 199.979,
      "end": 200.039,
      "type": "word"
    },
    {
      "text": " ",
      "start": 200.039,
      "end": 200.039,
      "type": "spacing"
    },
    {
      "text": "antoným",
      "start": 200.039,
      "end": 200.579,
      "type": "word"
    },
    {
      "text": " ",
      "start": 200.579,
      "end": 200.599,
      "type": "spacing"
    },
    {
      "text": "k",
      "start": 200.599,
      "end": 200.619,
      "type": "word"
    },
    {
      "text": " ",
      "start": 200.619,
      "end": 200.659,
      "type": "spacing"
    },
    {
      "text": "slovu",
      "start": 200.659,
      "end": 200.979,
      "type": "word"
    },
    {
      "text": " ",
      "start": 200.979,
      "end": 201.059,
      "type": "spacing"
    },
    {
      "text": "smutný?",
      "start": 201.059,
      "end": 201.799,
      "type": "word"
    },
    {
      "text": " ",
      "start": 201.799,
      "end": 202.899,
      "type": "spacing"
    },
    {
      "text": "Šťastný,",
      "start": 202.899,
      "end": 203.639,
      "type": "word"
    },
    {
      "text": " ",
      "start": 203.639,
      "end": 203.659,
      "type": "spacing"
    },
    {
      "text": "veselý,",
      "start": 203.659,
      "end": 204.179,
      "type": "word"
    },
    {
      "text": " ",
      "start": 204.179,
      "end": 204.179,
      "type": "spacing"
    },
    {
      "text": "radostný,",
      "start": 204.179,
      "end": 205.079,
      "type": "word"
    },
    {
      "text": " ",
      "start": 205.079,
      "end": 205.139,
      "type": "spacing"
    },
    {
      "text": "akékoľvek",
      "start": 205.139,
      "end": 205.859,
      "type": "word"
    },
    {
      "text": " ",
      "start": 205.859,
      "end": 205.859,
      "type": "spacing"
    },
    {
      "text": "antonym.",
      "start": 205.859,
      "end": 206.479,
      "type": "word"
    },
    {
      "text": " ",
      "start": 206.479,
      "end": 206.559,
      "type": "spacing"
    },
    {
      "text": "Čiže",
      "start": 206.559,
      "end": 206.919,
      "type": "word"
    },
    {
      "text": " ",
      "start": 206.919,
      "end": 207.439,
      "type": "spacing"
    },
    {
      "text": "aj",
      "start": 207.439,
      "end": 207.679,
      "type": "word"
    },
    {
      "text": " ",
      "start": 207.679,
      "end": 207.679,
      "type": "spacing"
    },
    {
      "text": "veď",
      "start": 207.679,
      "end": 208.019,
      "type": "word"
    },
    {
      "text": " ",
      "start": 208.019,
      "end": 208.139,
      "type": "spacing"
    },
    {
      "text": "ich",
      "start": 208.139,
      "end": 208.159,
      "type": "word"
    },
    {
      "text": " ",
      "start": 208.159,
      "end": 208.159,
      "type": "spacing"
    },
    {
      "text": "prakticky",
      "start": 208.159,
      "end": 208.839,
      "type": "word"
    },
    {
      "text": " ",
      "start": 208.839,
      "end": 208.939,
      "type": "spacing"
    },
    {
      "text": "z",
      "start": 208.939,
      "end": 209.039,
      "type": "word"
    },
    {
      "text": " ",
      "start": 209.039,
      "end": 209.039,
      "type": "spacing"
    },
    {
      "text": "toho",
      "start": 209.039,
      "end": 209.259,
      "type": "word"
    },
    {
      "text": " ",
      "start": 209.259,
      "end": 209.359,
      "type": "spacing"
    },
    {
      "text": "textu.",
      "start": 209.359,
      "end": 210.139,
      "type": "word"
    },
    {
      "text": " ",
      "start": 210.139,
      "end": 210.519,
      "type": "spacing"
    },
    {
      "text": "Z",
      "start": 210.519,
      "end": 210.539,
      "type": "word"
    },
    {
      "text": " ",
      "start": 210.539,
      "end": 210.539,
      "type": "spacing"
    },
    {
      "text": "toho",
      "start": 210.539,
      "end": 210.619,
      "type": "word"
    },
    {
      "text": " ",
      "start": 210.619,
      "end": 210.899,
      "type": "spacing"
    },
    {
      "text": "činy.",
      "start": 210.899,
      "end": 211.279,
      "type": "word"
    },
    {
      "text": " ",
      "start": 211.279,
      "end": 212.039,
      "type": "spacing"
    },
    {
      "text": "Tá",
      "start": 212.039,
      "end": 212.359,
      "type": "word"
    },
    {
      "text": " ",
      "start": 212.359,
      "end": 212.399,
      "type": "spacing"
    },
    {
      "text": "písomka.",
      "start": 212.399,
      "end": 212.899,
      "type": "word"
    },
    {
      "text": " ",
      "start": 212.899,
      "end": 214.119,
      "type": "spacing"
    },
    {
      "text": "Zatvor",
      "start": 214.119,
      "end": 214.359,
      "type": "word"
    },
    {
      "text": " ",
      "start": 214.359,
      "end": 214.399,
      "type": "spacing"
    },
    {
      "text": "úst,",
      "start": 214.399,
      "end": 214.539,
      "type": "word"
    },
    {
      "text": " ",
      "start": 214.539,
      "end": 214.559,
      "type": "spacing"
    },
    {
      "text": "povedzme,",
      "start": 214.559,
      "end": 214.639,
      "type": "word"
    },
    {
      "text": " ",
      "start": 214.639,
      "end": 214.899,
      "type": "spacing"
    },
    {
      "text": "že",
      "start": 214.899,
      "end": 214.999,
      "type": "word"
    },
    {
      "text": " ",
      "start": 214.999,
      "end": 214.999,
      "type": "spacing"
    },
    {
      "text": "zajtra",
      "start": 214.999,
      "end": 215.019,
      "type": "word"
    },
    {
      "text": " ",
      "start": 215.019,
      "end": 215.079,
      "type": "spacing"
    },
    {
      "text": "budem",
      "start": 215.079,
      "end": 215.519,
      "type": "word"
    },
    {
      "text": " ",
      "start": 215.519,
      "end": 215.539,
      "type": "spacing"
    },
    {
      "text": "robiť,",
      "start": 215.539,
      "end": 216.099,
      "type": "word"
    },
    {
      "text": " ",
      "start": 216.099,
      "end": 216.119,
      "type": "spacing"
    },
    {
      "text": "čo",
      "start": 216.119,
      "end": 216.259,
      "type": "word"
    },
    {
      "text": " ",
      "start": 216.259,
      "end": 216.259,
      "type": "spacing"
    },
    {
      "text": "mám",
      "start": 216.259,
      "end": 216.439,
      "type": "word"
    },
    {
      "text": " ",
      "start": 216.439,
      "end": 216.559,
      "type": "spacing"
    },
    {
      "text": "Hamleta",
      "start": 216.559,
      "end": 217.239,
      "type": "word"
    },
    {
      "text": " ",
      "start": 217.239,
      "end": 218.879,
      "type": "spacing"
    },
    {
      "text": "vypraviť.",
      "start": 218.879,
      "end": 220.619,
      "type": "word"
    },
    {
      "text": " ",
      "start": 220.619,
      "end": 220.719,
      "type": "spacing"
    },
    {
      "text": "Ja",
      "start": 220.719,
      "end": 222.819,
      "type": "word"
    },
    {
      "text": " ",
      "start": 222.819,
      "end": 222.819,
      "type": "spacing"
    },
    {
      "text": "som",
      "start": 222.819,
      "end": 223.219,
      "type": "word"
    },
    {
      "text": " ",
      "start": 223.219,
      "end": 223.219,
      "type": "spacing"
    },
    {
      "text": "zajtrajšok",
      "start": 223.219,
      "end": 223.879,
      "type": "word"
    },
    {
      "text": " ",
      "start": 223.879,
      "end": 223.999,
      "type": "spacing"
    },
    {
      "text": "už",
      "start": 223.999,
      "end": 224.239,
      "type": "word"
    },
    {
      "text": " ",
      "start": 224.239,
      "end": 224.399,
      "type": "spacing"
    },
    {
      "text": "dávno",
      "start": 224.399,
      "end": 224.799,
      "type": "word"
    },
    {
      "text": " ",
      "start": 224.799,
      "end": 226.039,
      "type": "spacing"
    },
    {
      "text": "nebudem.",
      "start": 226.039,
      "end": 226.399,
      "type": "word"
    },
    {
      "text": " ",
      "start": 226.399,
      "end": 226.959,
      "type": "spacing"
    },
    {
      "text": "Radek",
      "start": 226.959,
      "end": 227.279,
      "type": "word"
    },
    {
      "text": " ",
      "start": 227.279,
      "end": 227.279,
      "type": "spacing"
    },
    {
      "text": "taký,",
      "start": 227.279,
      "end": 227.479,
      "type": "word"
    },
    {
      "text": " ",
      "start": 227.479,
      "end": 227.479,
      "type": "spacing"
    },
    {
      "text": "že",
      "start": 227.479,
      "end": 227.599,
      "type": "word"
    },
    {
      "text": " ",
      "start": 227.599,
      "end": 227.619,
      "type": "spacing"
    },
    {
      "text": "čo",
      "start": 227.619,
      "end": 227.799,
      "type": "word"
    },
    {
      "text": " ",
      "start": 227.799,
      "end": 227.799,
      "type": "spacing"
    },
    {
      "text": "zajtra,",
      "start": 227.799,
      "end": 228.159,
      "type": "word"
    },
    {
      "text": " ",
      "start": 228.159,
      "end": 228.159,
      "type": "spacing"
    },
    {
      "text": "čo?",
      "start": 228.159,
      "end": 228.439,
      "type": "word"
    },
    {
      "text": " ",
      "start": 228.439,
      "end": 229.519,
      "type": "spacing"
    },
    {
      "text": "Uzávierky.",
      "start": 229.519,
      "end": 234.599,
      "type": "word"
    }
  ]
}